cloud_storage_client/__init__.py
cloud_storage_client/as3.py
cloud_storage_client/azure.py
cloud_storage_client/exceptions.py
cloud_storage_client/file_system.py
cloud_storage_client/ftp.py
cloud_storage_client/gcloud.py
cloud_storage_client/gcloud_access_secret.py
cloud_storage_client/sftp.py
cloud_storage_client/storage.py
cloud_storage_client/storage_adapter.py
cloud_storage_client-2.4.3.dist-info/LICENSE.txt
cloud_storage_client-2.4.3.dist-info/METADATA
cloud_storage_client-2.4.3.dist-info/WHEEL
cloud_storage_client-2.4.3.dist-info/top_level.txt
cloud_storage_client-2.4.3.dist-info/RECORD
