Metadata-Version: 2.1
Name: cloud-storage-client
Version: 2.4.3
Summary: UNKNOWN
Home-page: https://pypi.org/project/cloud-storage-client/
Author: Pablo Aguirre
Author-email: paguirrerubio@gmail.com
License: MIT
Platform: UNKNOWN
License-File: LICENSE.txt
Requires-Dist: botocore (==1.12.250)
Requires-Dist: boto3 (==1.9.250)
Requires-Dist: google-api-core (==1.22.4)
Requires-Dist: google-cloud-core (==1.4.3)
Requires-Dist: google-cloud-storage (==1.32.0)
Requires-Dist: azure-storage-blob (==12.3.0)
Requires-Dist: pysftp (==0.2.9)
Requires-Dist: ssh-agent-setup (==1.0.1)
